glo/__init__.py
glo-0.0.0.dev1.dist-info/DESCRIPTION.rst
glo-0.0.0.dev1.dist-info/METADATA
glo-0.0.0.dev1.dist-info/RECORD
glo-0.0.0.dev1.dist-info/WHEEL
glo-0.0.0.dev1.dist-info/metadata.json
glo-0.0.0.dev1.dist-info/top_level.txt
