Metadata-Version: 2.0
Name: glo
Version: 0.0.0.dev1
Summary: Lib for using Glo monitoring in Python.
Home-page: https://github.com/andersroos/glo
Author: Anders Roos
Author-email: anders.roos@gmail.com
License: MIT
Platform: UNKNOWN
Classifier: Development Status :: 1 - Planning
Classifier: Intended Audience :: Developers
Classifier: Intended Audience :: System Administrators
Classifier: License :: OSI Approved :: MIT License
Classifier: Programming Language :: Python :: 3
Classifier: Topic :: System :: Monitoring
